MANIFEST.in
README.md
setup.cfg
setup.py
version.txt
src/vdk/api/data_job.py
src/vdk/api/job_input.py
src/vdk/api/plugin/connection_hook_spec.py
src/vdk/api/plugin/core_hook_spec.py
src/vdk/api/plugin/hook_markers.py
src/vdk/api/plugin/plugin_input.py
src/vdk/api/plugin/plugin_registry.py
src/vdk/api/plugin/plugin_utils.py
src/vdk/internal/cli_entry.py
src/vdk/internal/vdk_build_info.py
src/vdk/internal/builtin_plugins/builtin_hook_impl.py
src/vdk/internal/builtin_plugins/internal_hookspecs.py
src/vdk/internal/builtin_plugins/config/config_help.py
src/vdk/internal/builtin_plugins/config/job_config.py
src/vdk/internal/builtin_plugins/config/log_config.py
src/vdk/internal/builtin_plugins/config/vdk_config.py
src/vdk/internal/builtin_plugins/connection/connection_hooks.py
src/vdk/internal/builtin_plugins/connection/connection_plugin.py
src/vdk/internal/builtin_plugins/connection/decoration_cursor.py
src/vdk/internal/builtin_plugins/connection/execution_cursor.py
src/vdk/internal/builtin_plugins/connection/managed_connection_base.py
src/vdk/internal/builtin_plugins/connection/managed_cursor.py
src/vdk/internal/builtin_plugins/connection/proxy_cursor.py
src/vdk/internal/builtin_plugins/connection/recovery_cursor.py
src/vdk/internal/builtin_plugins/connection/impl/router.py
src/vdk/internal/builtin_plugins/connection/impl/wrapped_connection.py
src/vdk/internal/builtin_plugins/connection/pep249/interfaces.py
src/vdk/internal/builtin_plugins/debug/debug.py
src/vdk/internal/builtin_plugins/ingestion/ingester_base.py
src/vdk/internal/builtin_plugins/ingestion/ingester_configuration.py
src/vdk/internal/builtin_plugins/ingestion/ingester_configuration_plugin.py
src/vdk/internal/builtin_plugins/ingestion/ingester_router.py
src/vdk/internal/builtin_plugins/ingestion/ingester_utils.py
src/vdk/internal/builtin_plugins/job_properties/base_properties_impl.py
src/vdk/internal/builtin_plugins/job_properties/cached_properties.py
src/vdk_core.egg-info/PKG-INFO
src/vdk_core.egg-info/SOURCES.txt
src/vdk_core.egg-info/dependency_links.txt
src/vdk_core.egg-info/entry_points.txt
src/vdk_core.egg-info/not-zip-safe
src/vdk_core.egg-info/requires.txt
src/vdk_core.egg-info/top_level.txt