Metadata-Version: 2.1
Name: vdk-core
Version: 0.3.912884507
Summary: Versatile Data Kit SDK Core
Home-page: https://github.com/vmware/versatile-data-kit/projects/vdk-core
Author: VMware Inc.
Author-email: taurus@vmware.com
Project-URL: Documentation, https://github.com/vmware/versatile-data-kit/projects/vdk-core/README.md
Project-URL: Source, https://github.com/vmware/versatile-data-kit/projects/vdk-core
Platform: any
Classifier: Development Status :: 4 - Beta
Classifier: License :: OSI Approved :: Apache Software License
Classifier: Programming Language :: Python
Classifier: Programming Language :: Python :: 3.7
Classifier: Programming Language :: Python :: 3.8
Classifier: Programming Language :: Python :: 3.9
Classifier: Programming Language :: Python :: 3.10
Classifier: Programming Language :: Python :: 3.11
Requires-Python: <4,>=3.7
